fancypipe/__init__.py
fancypipe/fancypipe.py
fancypipe-0.5.3.dist-info/DESCRIPTION.rst
fancypipe-0.5.3.dist-info/LICENSE.txt
fancypipe-0.5.3.dist-info/METADATA
fancypipe-0.5.3.dist-info/RECORD
fancypipe-0.5.3.dist-info/WHEEL
fancypipe-0.5.3.dist-info/metadata.json
fancypipe-0.5.3.dist-info/top_level.txt
